listdupes/__init__.py
listdupes/main.py
listdupes-2025.7.13.2.dist-info/METADATA
listdupes-2025.7.13.2.dist-info/WHEEL
listdupes-2025.7.13.2.dist-info/entry_points.txt
listdupes-2025.7.13.2.dist-info/licenses/LICENSE
listdupes-2025.7.13.2.dist-info/RECORD
