Metadata-Version: 2.4
Name: listdupes
Version: 2025.7.13.2
Summary: A tool to list duplicate files in a directory tree
Project-URL: Homepage, https://github.com/acetylen/listdupes
Project-URL: Issues, https://github.com/acetylen/listdupes/issues
Author: Emil Tylén
License-Expression: GPL-3.0-or-later
License-File: LICENSE
Keywords: cli,duplicate,listdupes,tool
Classifier: Development Status :: 4 - Beta
Classifier: Environment :: Console
Classifier: Intended Audience :: Developers
Classifier: Intended Audience :: System Administrators
Classifier: Programming Language :: Python :: 3
Classifier: Programming Language :: Python :: 3.10
Classifier: Programming Language :: Python :: 3.11
Classifier: Programming Language :: Python :: 3.12
Classifier: Programming Language :: Python :: 3.13
Requires-Python: >=3.10
